acm_dl_searcher/__init__.py
acm_dl_searcher/__main__.py
acm_dl_searcher/_utils.py
acm_dl_searcher/cli.py
acm_dl_searcher/search_operations.py
acm_dl_searcher/templates/search_result.html
acm_dl_searcher-0.1.0a3.dist-info/entry_points.txt
acm_dl_searcher-0.1.0a3.dist-info/LICENSE
acm_dl_searcher-0.1.0a3.dist-info/WHEEL
acm_dl_searcher-0.1.0a3.dist-info/METADATA
acm_dl_searcher-0.1.0a3.dist-info/RECORD
