Metadata-Version: 2.1
Name: acm-dl-searcher
Version: 0.1.0a3
Summary: Top-level package for ACM DL Searcher.
Home-page: https://github.com/ahmed-shariff/acm_dl_searcher
License: MIT
Author: Ahmed Shariff
Author-email: shariff.mfa@outlook.com
Requires-Python: >=3.6,<4.0
Classifier: Development Status :: 2 - Pre-Alpha
Classifier: Intended Audience :: Developers
Classifier: License :: OSI Approved :: MIT License
Classifier: Natural Language :: English
Classifier: Programming Language :: Python :: 3
Classifier: Programming Language :: Python :: 3.5
Classifier: Programming Language :: Python :: 3.6
Classifier: Programming Language :: Python :: 3.7
Classifier: Programming Language :: Python :: 3.8
Classifier: Programming Language :: Python :: 3.9
Requires-Dist: beautifulsoup4 (>=4.9.3,<5.0.0)
Requires-Dist: bibtexparser (>=1.2.0,<2.0.0)
Requires-Dist: click (>=7.1.2,<8.0.0)
Requires-Dist: fuzzysearch (>=0.7.3,<0.8.0)
Requires-Dist: liquidpy (>=0.6.2,<0.7.0)
Requires-Dist: minilog (>=1.5,<2.0)
Requires-Dist: requests (>=2.24.0,<3.0.0)
Requires-Dist: tabulate (>=0.8.7,<0.9.0)
Requires-Dist: tqdm (>=4.51.0,<5.0.0)
